camppy2/__init__.py
camppy2/camp1.py
camppy2-1.3.dist-info/METADATA
camppy2-1.3.dist-info/WHEEL
camppy2-1.3.dist-info/top_level.txt
camppy2-1.3.dist-info/RECORD
