Metadata-Version: 2.1
Name: camppy2
Version: 1.3
Summary: CXMP MODULE
Author: CAMP
Author-email: contactcampsmm@gmail.com
Classifier: Programming Language :: Python :: 3
Classifier: License :: OSI Approved :: MIT License
Classifier: Operating System :: OS Independent
Requires-Python: >=3.6
Requires-Dist: requests
Requires-Dist: user-agent
